pywwwget.py
pywwwgetmini.py
pywwwgetold.py
pywww_get-2.1.6.data/scripts/pyhttpserv.py
pywww_get-2.1.6.data/scripts/pywwwget-dl.py
pywww_get-2.1.6.data/scripts/pywwwgetold-dl.py
pywww_get-2.1.6.dist-info/licenses/LICENSE
pywww_get-2.1.6.dist-info/METADATA
pywww_get-2.1.6.dist-info/WHEEL
pywww_get-2.1.6.dist-info/top_level.txt
pywww_get-2.1.6.dist-info/zip-safe
pywww_get-2.1.6.dist-info/RECORD
