Metadata-Version: 2.4
Name: PyWWW-Get
Version: 2.1.6
Summary: Python libary/module to download files.
Home-page: https://github.com/GameMaker2k/PyWWW-Get
Download-URL: https://github.com/GameMaker2k/PyWWW-Get/archive/master.tar.gz
Author: Kazuki Przyborowski
Author-email: Kazuki Przyborowski <kazuki.przyborowski@gmail.com>
Maintainer: Kazuki Przyborowski
Maintainer-email: kazuki.przyborowski@gmail.com
License: BSD-3-Clause
Platform: OS Independent
License-File: LICENSE
Dynamic: author
Dynamic: download-url
Dynamic: home-page
Dynamic: license-file
Dynamic: maintainer
Dynamic: maintainer-email
Dynamic: platform
